alembicverify/__init__.py
alembicverify/pyfixtures.py
alembicverify/util.py
docs/__init__.py
docs/testing/__init__.py
docs/testing/conftest.py
docs/testing/models.py
docs/testing/test_alembic.py
docs/testing/test_example.py
docs/testing/test_unittest.py
alembic_verify-0.1.4.dist-info/zip-safe
alembic_verify-0.1.4.dist-info/top_level.txt
alembic_verify-0.1.4.dist-info/entry_points.txt
alembic_verify-0.1.4.dist-info/METADATA
alembic_verify-0.1.4.dist-info/DESCRIPTION.rst
alembic_verify-0.1.4.dist-info/metadata.json
alembic_verify-0.1.4.dist-info/WHEEL
alembic_verify-0.1.4.dist-info/RECORD
